ukb/__init__.py
ukb/category.py
ukb/dataset.py
ukb_interface-0.1.0.dist-info/LICENSE
ukb_interface-0.1.0.dist-info/METADATA
ukb_interface-0.1.0.dist-info/WHEEL
ukb_interface-0.1.0.dist-info/top_level.txt
ukb_interface-0.1.0.dist-info/RECORD
