Metadata-Version: 2.1
Name: ukb-interface
Version: 0.1.0
Summary: UK Biobank Interface
Author-email: Sifeng Wang <wangsifeng@bupt.edu.cn>
Project-URL: Homepage, https://github.com/SifengWang/UKB-Interface
Project-URL: Bug Tracker, https://github.com/SifengWang/UKB-Interface/issues
Classifier: Programming Language :: Python :: 3
Classifier: Operating System :: OS Independent
Requires-Python: >=3.8
License-File: LICENSE
